bedrocked/__errors__.py
bedrocked/__init__.py
bedrocked/bedrock.py
bedrocked/sherlock.py
bedrocked/config/__init__.py
bedrocked/config/conf.py
bedrocked/config/enviro.py
bedrocked/config/features.py
bedrocked/config/layering.py
bedrocked/config/meta_conf.py
bedrocked/performance/__init__.py
bedrocked/reporting/__init__.py
bedrocked/reporting/logged.py
bedrocked/reporting/reported.py
bedrocked/working/__init__.py
bedrocked/working/background.py
bedrocked/working/remote.py
bedrocked-0.1.5.dist-info/LICENSE.md
bedrocked-0.1.5.dist-info/METADATA
bedrocked-0.1.5.dist-info/WHEEL
bedrocked-0.1.5.dist-info/top_level.txt
bedrocked-0.1.5.dist-info/RECORD
