Metadata-Version: 2.2
Name: bedrocked
Version: 0.1.5
Summary: Foundation library offering essential utilities for configuration, logging, error handling, and more.
Author-email: DirtyWork Solutions Limited <bedrocked@open.dirtywork.solutions>
License: # MIT License
Project-URL: Homepage, https://open.dirtywork.solutions/bedrocked
Project-URL: Documentation, https://github.com/DirtyWork-Solutions/Bedrocked/docs/INDEX.md
Project-URL: Source, https://github.com/DirtyWork-Solutions/Bedrocked
Project-URL: Issues, https://github.com/DirtyWork-Solutions/Bedrocked/tree/main/.github/ISSUE_TEMPLATE
Classifier: Programming Language :: Python :: 3
Classifier: Programming Language :: Python :: 3.13
Classifier: Programming Language :: Python :: Implementation :: CPython
Classifier: License :: OSI Approved :: MIT License
Classifier: Operating System :: OS Independent
Classifier: Development Status :: 2 - Pre-Alpha
Classifier: Environment :: Console
Classifier: Framework :: Pytest
Classifier: Framework :: Pydantic
Classifier: Intended Audience :: Developers
Classifier: Topic :: System
Classifier: Topic :: System :: Logging
Classifier: Topic :: Software Development :: Libraries :: Python Modules
Classifier: Topic :: Utilities
Classifier: Topic :: System :: Installation/Setup
Requires-Python: >=3.13
License-File: LICENSE.md
Requires-Dist: pyforged~=0.2.4
Requires-Dist: loguru~=0.7.3
Requires-Dist: omegaconf~=2.3.0
